pmini_sdk_python/__init__.py
pmini_sdk_python/camera.py
pmini_sdk_python/common.py
pmini_sdk_python/drone_client.py
pmini_sdk_python/generated/__init__.py
pmini_sdk_python/generated/drone_pb2.py
pmini_sdk_python/generated/drone_pb2.pyi
pmini_sdk_python/generated/drone_pb2_grpc.py
pmini_sdk_python/high_level_commander.py
pmini_sdk_python/low_level_commander.py
pmini_sdk_python/mavlink_client.py
pmini_sdk_python/pmini.py
pmini_sdk_python/pmini_server/__init__.py
pmini_sdk_python/pmini_server/server.py
pmini_sdk_python/sync_drone_client.py
pmini_sdk-1.1.1.dist-info/METADATA
pmini_sdk-1.1.1.dist-info/WHEEL
pmini_sdk-1.1.1.dist-info/entry_points.txt
pmini_sdk-1.1.1.dist-info/RECORD
