Metadata-Version: 2.4
Name: pmini_sdk
Version: 1.1.1
Summary: Python SDK for Pmini quadcopter
License: Proprietary
Keywords: drone,quadcopter,mavlink,sdk
Author: RegisLab
Requires-Python: >=3.9,<4.0
Classifier: Development Status :: 4 - Beta
Classifier: Intended Audience :: Developers
Classifier: License :: Other/Proprietary License
Classifier: Programming Language :: Python :: 3
Classifier: Programming Language :: Python :: 3.9
Classifier: Programming Language :: Python :: 3.10
Classifier: Programming Language :: Python :: 3.11
Classifier: Programming Language :: Python :: 3.12
Classifier: Programming Language :: Python :: 3.13
Classifier: Programming Language :: Python :: 3.14
Classifier: Topic :: Scientific/Engineering
Classifier: Topic :: Software Development :: Libraries :: Python Modules
Requires-Dist: dash (==2.17.1)
Requires-Dist: grpcio (>=1.74.0,<2.0.0)
Requires-Dist: grpcio-tools (>=1.74.0,<2.0.0)
Requires-Dist: jinja2 (>=3.1.4,<4.0.0)
Requires-Dist: plotly (==5.22.0)
Requires-Dist: pymavlink (>=2.4.41,<3.0.0)
Project-URL: Homepage, https://github.com/RegisLab/pmini-sdk
Project-URL: Repository, https://github.com/RegisLab/pmini-sdk
